nbdev example/__init__.py
nbdev example/_nbdev.py
nbdev example/card.py
nbdev_example/__init__.py
nbdev_example/_nbdev.py
nbdev_example/card.py
nbdev_example/deck.py
nbdev_example-0.0.1.dist-info/LICENSE
nbdev_example-0.0.1.dist-info/METADATA
nbdev_example-0.0.1.dist-info/WHEEL
nbdev_example-0.0.1.dist-info/entry_points.txt
nbdev_example-0.0.1.dist-info/top_level.txt
nbdev_example-0.0.1.dist-info/RECORD
